{
  "timestamp": "2026-05-20T04:16:32",
  "data": {
    "latitude": 35.7,
    "longitude": 139.6875,
    "generationtime_ms": 0.10669231414794922,
    "utc_offset_seconds": 32400,
    "timezone": "Asia/Tokyo",
    "timezone_abbreviation": "GMT+9",
    "elevation": 40.0,
    "daily_units": {
      "time": "iso8601",
      "weathercode": "wmo code",
      "temperature_2m_max": "°C",
      "temperature_2m_min": "°C"
    },
    "daily": {
      "time": [
        "2026-05-20",
        "2026-05-21",
        "2026-05-22",
        "2026-05-23",
        "2026-05-24",
        "2026-05-25",
        "2026-05-26"
      ],
      "weathercode": [
        51,
        65,
        61,
        3,
        51,
        3,
        3
      ],
      "temperature_2m_max": [
        28.0,
        20.0,
        13.9,
        19.8,
        22.6,
        28.0,
        25.6
      ],
      "temperature_2m_min": [
        16.4,
        14.0,
        12.0,
        11.0,
        13.1,
        16.6,
        17.1
      ]
    }
  }
}